{
    "Copyright":   "Copyright (C) 2015 - 2020 Jeffrey Gilliam",
    "License":     "Apache License 2.0",
    "Description": "",
    "MfrLogo":     "com/SIMRacingApps/Cars/ford.png",
    "Comment":     "Gauges not defined here are inherieted from Car.json",
    "Gauges": {
        "Tachometer": {
            "default": {
                "Name":              "RPM",
                "TypeName":          "x1000",
                "UOM":               "rpm",
                "Multiplier":        0.001,
                "Minimum":           0.0,
                "Maximum":           8.0,
                "MajorIncrement":    1.0,
                "MinorIncrement":    0.2,
                "StateAscending":    true
            }
        },
        "Gear": {
            "default": {
                "Name":              "GEAR",
                "TypeName":          "",
                "UOM":               "",
                "Minimum":           -1.0,
                "Maximum":           6.0,
                "MajorIncrement":    1.0,
                "MinorIncrement":    1.0,
                "CapacityMinimum":   -1.0,
                "CapacityMaximum":   6.0,
                "CapacityIncrement": 1.0,
                "StateAscending":    true
            }
        },
        "OilPressure": {
            "default": {
                "Name":              "OIL",
                "TypeName":          "PRESSURE",
                "UOM":               "psi",
                "Minimum":           0.0,
                "Maximum":           100.0,
                "MajorIncrement":    20.0,
                "MinorIncrement":    10.0,
                "StateAscending":    false,
                "States": {
                    "CRITICAL": {"Start": 0.0,  "End": 5.0},
                    "WARNING":  {"Start": 5.0,  "End": 10.0}
                }
            }
        },
        "FuelLevel": {
            "default": {
                "Name":              "FUEL",
                "TypeName":          "LEVEL",
                "UOM":               "gal",
                "Minimum":           0.0,
                "Maximum":           24.0,
                "MajorIncrement":    2.0,
                "MinorIncrement":    1.0,
                "CapacityMinimum":   0.0,
                "CapacityMaximum":   23.78,
                "CapacityIncrement": 1.32,
                "IsFixed":           false,
                "IsChangable":       true,
                "OnResetChange":     true,
                "StateAscending":    false,
                "States": {
                    "CRITICAL": {"Start": 0.0, "End": 1.0},
                    "WARNING":  {"Start": 1.0, "End": 2.0}
                }
            }
        },
        "TractionControlRear": {
            "default": {
                "Name":              "TRACTION CONTROL",
                "TypeName":          "REAR",
                "UOM":               "",
                "imperial":          "",
                "metric":            "",
                "StateAscending":    false,
                "Minimum":           1.0,
                "Maximum":           3.0,
                "MajorIncrement":    1.0,
                "MinorIncrement":    1.0,
                "CapacityMinimum":   1.0,
                "CapacityMaximum":   3.0,
                "CapacityIncrement": 1.0,
                "IsFixed":           false
            }
        }
    }
}
